{
  "valid": {
    "newPassword": "Newpass2@24",
    "confirmPassword": "Newpass2@24",
    "successMessage": "Profile updated successfully"
  },
  "duplicate": {
    "newPassword": "Newpass2@24",
    "confirmPassword": "Newpass2@24",
    "errorMessage": "New password cannot be the same as current password"
  },
  "mismatch": {
    "newPassword": "Newpass2@24",
    "confirmPassword": "Newpass2@25",
    "errorMessage": "Passwords do not match"
  },
  "invalid": {
    "newPassword": "123456",
    "confirmPassword": "123456",
    "passwordError": "Password must meet the required format"
  },
  "user": {
    "email": "ha@email.com",
    "password": "123456"
  }
}